setup.cfg
setup.py
pyI18n/I18n.py
pyI18n/__init__.py
pyI18n.egg-info/PKG-INFO
pyI18n.egg-info/SOURCES.txt
pyI18n.egg-info/dependency_links.txt
pyI18n.egg-info/not-zip-safe
pyI18n.egg-info/top_level.txt