Metadata-Version: 1.0
Name: pyI18n
Version: 1.0.1
Summary: Package to internationalize your program
Home-page: UNKNOWN
Author: UNKNOWN
Author-email: andrewklad@yandex.ru
License: UNKNOWN
Platform: UNKNOWN
